e_protonvpn_cli/__init__.py
e_protonvpn_cli/__main__.py
e_protonvpn_cli/cli.py
e_protonvpn_cli/connection.py
e_protonvpn_cli/constants.py
e_protonvpn_cli/country_codes.py
e_protonvpn_cli/logger.py
e_protonvpn_cli/utils.py
e_protonvpn_cli/templates/openvpn_template.j2
e_protonvpn_cli-2.2.9.dist-info/AUTHORS
e_protonvpn_cli-2.2.9.dist-info/LICENSE
e_protonvpn_cli-2.2.9.dist-info/METADATA
e_protonvpn_cli-2.2.9.dist-info/WHEEL
e_protonvpn_cli-2.2.9.dist-info/entry_points.txt
e_protonvpn_cli-2.2.9.dist-info/top_level.txt
e_protonvpn_cli-2.2.9.dist-info/RECORD
