Metadata-Version: 2.1
Name: e-protonvpn-cli
Version: 2.2.9
Summary: Linux command-line client for ProtonVPN
Home-page: https://github.com/er888kh/linux-cli-community
Author: Erfan Khadem
Author-email: erfankhademerkh@gmail.com
License: GPLv3
Platform: UNKNOWN
Classifier: Development Status :: 4 - Beta
Classifier: Environment :: Console
Classifier: License :: OSI Approved :: GNU General Public License v3 (GPLv3)
Classifier: Programming Language :: Python
Classifier: Programming Language :: Python :: 3
Classifier: Programming Language :: Python :: 3.5
Classifier: Programming Language :: Python :: 3.6
Classifier: Programming Language :: Python :: 3.7
Classifier: Programming Language :: Python :: 3.8
Classifier: Programming Language :: Python :: 3.9
Requires-Python: >=3.5
Requires-Dist: docopt
Requires-Dist: jinja2
Requires-Dist: pythondialog
Requires-Dist: requests
